<?xml version="1.0" encoding="UTF-8"?><td:AuctionData xmlns:td="http://www.treasurydirect.gov/" xmlns:xsi="http://www.w3.org/2001/XMLSchema-instance" xsi:schemaLocation="http://www.treasurydirect.gov/ https://www.treasurydirect.gov/xsd/Auction_v5_0_0.xsd">
<AuctionAnnouncement>
<SecurityTermWeekYear>10-YEAR</SecurityTermWeekYear>
<SecurityTermDayMonth>0-MONTH</SecurityTermDayMonth>
<SecurityType>NOTE</SecurityType>
<CUSIP>91282CEP2</CUSIP>
<AnnouncementDate>2022-05-04</AnnouncementDate>
<AuctionDate>2022-05-11</AuctionDate>
<IssueDate>2022-05-16</IssueDate>
<MaturityDate>2032-05-15</MaturityDate>
<OfferingAmount>36.000</OfferingAmount>
<CompetitiveTenderAccepted>Y</CompetitiveTenderAccepted>
<NonCompetitiveTenderAccepted>Y</NonCompetitiveTenderAccepted>
<TreasuryDirectTenderAccepted>Y</TreasuryDirectTenderAccepted>
<TypeOfAuction>SINGLE PRICE</TypeOfAuction>
<CompetitiveClosingTime>13:00</CompetitiveClosingTime>
<NonCompetitiveClosingTime>12:00</NonCompetitiveClosingTime>
<NetLongPositionReport>12600000000.0</NetLongPositionReport>
<MaxAward>12600000000</MaxAward>
<MaxSingleBid>12600000000</MaxSingleBid>
<CompetitiveBidDecimals>3</CompetitiveBidDecimals>
<CompetitiveBidIncrement>0.001</CompetitiveBidIncrement>
<AllocationPercentageDecimals>2</AllocationPercentageDecimals>
<MinBidAmount>100</MinBidAmount>
<MultiplesToBid>100</MultiplesToBid>
<MinToIssue>100</MinToIssue>
<MultiplesToIssue>100</MultiplesToIssue>
<MatureSecurityAmount>47846000000.0</MatureSecurityAmount>
<CurrentlyOutstanding/>
<SOMAIncluded>N</SOMAIncluded>
<SOMAHoldings>72083000000.0</SOMAHoldings>
<MaturingDate>2022-05-15</MaturingDate>
<FIMAIncluded>Y</FIMAIncluded>
<Series>C-2032</Series>
<InterestRate/>
<Spread/>
<FirstInterestPaymentDate>2022-11-15</FirstInterestPaymentDate>
<StandardInterestPayment/>
<FrequencyInterestPayment>SEMI-ANNUAL</FrequencyInterestPayment>
<StrippableIndicator>Y</StrippableIndicator>
<MinStripAmount>100</MinStripAmount>
<CorpusCUSIP>912821HY4</CorpusCUSIP>
<TINTCUSIP1/>
<TINTCUSIP2/>
<ReOpeningIndicator>N</ReOpeningIndicator>
<OriginalIssueDate/>
<BackDated>Y</BackDated>
<BackDatedDate>2022-05-15</BackDatedDate>
<LongShortNormalCoupon>N</LongShortNormalCoupon>
<LongShortCouponFirstIntPmt/>
<InflationIndexSecurity>N</InflationIndexSecurity>
<FloatingRate>N</FloatingRate>
<RefCPIIssueDate/>
<RefCPIDatedDate/>
<IndexRatioOnIssueDate/>
<CPIBasePeriod/>
<TIINConversionFactor/>
<AccruedInterest/>
<DatedDate>2022-05-15</DatedDate>
<AnnouncedCUSIP/>
<UnadjustedPrice/>
<UnadjustedAccruedInterest/>
<AnnouncementPDFName>A_20220504_3.pdf</AnnouncementPDFName>
<OriginalDatedDate/>
<AdjustedAmountCurrentlyOutstanding/>
<NLPExclusionAmount>0.0</NLPExclusionAmount>
<MaximumNonCompAward>5000000.0</MaximumNonCompAward>
<AdjustedAccruedInterest/>
<Callable>N</Callable>
<CallDate/>
</AuctionAnnouncement>
<AuctionResults>
<LongShortCouponFirstIntPmt/>
<PrimaryDealerTendered>52812000000</PrimaryDealerTendered>
<PrimaryDealerAccepted>4132000000</PrimaryDealerAccepted>
<DirectBidderTendered>8195000000</DirectBidderTendered>
<DirectBidderAccepted>6545000000</DirectBidderAccepted>
<IndirectBidderTendered>28490090000</IndirectBidderTendered>
<IndirectBidderAccepted>25272055600</IndirectBidderAccepted>
<CompetitiveTendered>89497090000</CompetitiveTendered>
<CompetitiveAccepted>35949055600</CompetitiveAccepted>
<NonCompetitiveAccepted>50979700</NonCompetitiveAccepted>
<SOMATendered>25194106800</SOMATendered>
<SOMAAccepted>25194106800</SOMAAccepted>
<FIMATendered>0</FIMATendered>
<FIMAAccepted>0</FIMAAccepted>
<TotalTendered>114742176500</TotalTendered>
<TotalAccepted>61194142100</TotalAccepted>
<BidToCoverRatio>2.49</BidToCoverRatio>
<ReleaseTime>13:02</ReleaseTime>
<AmountAcceptedBelowLowRate>5</AmountAcceptedBelowLowRate>
<HighAllocationPercentage>75.08</HighAllocationPercentage>
<LowDiscountRate/>
<HighDiscountRate/>
<MedianDiscountRate/>
<LowYield>2.800</LowYield>
<HighYield>2.943</HighYield>
<MedianYield>2.850</MedianYield>
<LowDiscountMargin/>
<HighDiscountMargin/>
<MedianDiscountMargin/>
<LowPrice/>
<HighPrice>99.414646</HighPrice>
<MedianPrice/>
<TIINConversionFactor/>
<AccruedInterest>0.07813</AccruedInterest>
<StandardInterestPayment>14.375</StandardInterestPayment>
<InterestRate>2.875</InterestRate>
<Spread/>
<OriginalCUSIP/>
<UnadjustedPrice/>
<UnadjustedAccruedInterest/>
<TreasuryDirectAccepted>24066700</TreasuryDirectAccepted>
<InvestmentRate/>
<AdjustedPrice/>
<AdjustedAccruedInterest/>
<IndexRatio/>
<FRNIndexDeterminationDate/>
<FRNIndexDeterminationRate/>
<ResultsPDFName>R_20220511_2.pdf</ResultsPDFName>
</AuctionResults>
</td:AuctionData>
